rust_category-0.2.0.dist-info/METADATA
rust_category-0.2.0.dist-info/WHEEL
rust_category/__init__.py
rust_category/rust_category.cpython-37m-x86_64-linux-gnu.so
rust_category-0.2.0.dist-info/RECORD
