Metadata-Version: 2.1
Name: rust_category
Version: 0.2.0
